[
  {
    "tracking_id": "#20462",
    "product_img": "/assets/demo.png",
    "product_name": "Hat",
    "customer": "Matt Dickerson",
    "date": "13/05/2022",
    "amount": 4.99,
    "payment_mode": "Transfer Bank",
    "status": "Delivered"
  },
  {
    "tracking_id": "#20463",
    "product_img": "/assets/demo.png",
    "product_name": "Shirt",
    "customer": "John Doe",
    "date": "14/05/2022",
    "amount": 19.99,
    "payment_mode": "Cash on Delivery",
    "status": "Process"
  },
  {
    "tracking_id": "#20464",
    "product_img": "/assets/demo.png",
    "product_name": "Laptop",
    "customer": "Jane Smith",
    "date": "15/05/2022",
    "amount": 699.99,
    "payment_mode": "Transfer Bank",
    "status": "Canceled"
  },
  {
    "tracking_id": "#20465",
    "product_img": "/assets/demo.png",
    "product_name": "Smartphone",
    "customer": "Bob Johnson",
    "date": "16/05/2022",
    "amount": 499.99,
    "payment_mode": "Cash on Delivery",
    "status": "Delivered"
  },
  {
    "tracking_id": "#20466",
    "product_img": "/assets/demo.png",
    "product_name": "Dress",
    "customer": "Alice Williams",
    "date": "17/05/2022",
    "amount": 49.99,
    "payment_mode": "Transfer Bank",
    "status": "Process"
  },
  {
    "tracking_id": "#20467",
    "product_img": "/assets/demo.png",
    "product_name": "Jacket",
    "customer": "Charlie Brown",
    "date": "18/05/2022",
    "amount": 79.99,
    "payment_mode": "Cash on Delivery",
    "status": "Canceled"
  },
  {
    "tracking_id": "#20468",
    "product_img": "/assets/demo.png",
    "product_name": "Skirt",
    "customer": "Eve Davis",
    "date": "19/05/2022",
    "amount": 39.99,
    "payment_mode": "Cash on Delivery",
    "status": "Delivered"
  },
  {
    "tracking_id": "#20469",
    "product_img": "/assets/demo.png",
    "product_name": "Tie",
    "customer": "Frank Miller",
    "date": "20/05/2022",
    "amount": 9.99,
    "payment_mode": "Cash on Delivery",
    "status": "Process"
  },
  {
    "tracking_id": "#20470",
    "product_img": "/assets/demo.png",
    "product_name": "Belt",
    "customer": "Grace Taylor",
    "date": "21/05/2022",
    "amount": 14.99,
    "payment_mode": "Transfer Bank",
    "status": "Canceled"
  },
  {
    "tracking_id": "#20471",
    "product_img": "/assets/demo.png",
    "product_name": "Socks",
    "customer": "Henry Clark",
    "date": "22/05/2022",
    "amount": 5.99,
    "payment_mode": "Cash on Delivery",
    "status": "Delivered"
  },
  {
    "tracking_id": "#20472",
    "product_img": "/assets/demo.png",
    "product_name": "Gloves",
    "customer": "Ivy Rodriguez",
    "date": "23/05/2022",
    "amount": 12.99,
    "payment_mode": "Transfer Bank",
    "status": "Process"
  },
  {
    "tracking_id": "#20473",
    "product_img": "/assets/demo.png",
    "product_name": "Scarf",
    "customer": "John Thompson",
    "date": "24/05/2022",
    "amount": 17.99,
    "payment_mode": "Cash on Delivery",
    "status": "Canceled"
  },
  {
    "tracking_id": "#20474",
    "product_img": "/assets/demo.png",
    "product_name": "Hat",
    "customer": "Kate Lee",
    "date": "25/05/2022",
    "amount": 4.99,
    "payment_mode": "Transfer Bank",
    "status": "Delivered"
  },
  {
    "tracking_id": "#20475",
    "product_img": "/assets/demo.png",
    "product_name": "Shirt",
    "customer": "Luke Wilson",
    "date": "26/05/2022",
    "amount": 19.99,
    "payment_mode": "Cash on Delivery",
    "status": "Process"
  },
  {
    "tracking_id": "#20476",
    "product_img": "/assets/demo.png",
    "product_name": "Camera",
    "customer": "Mia Garcia",
    "date": "27/05/2022",
    "amount": 299.99,
    "payment_mode": "Transfer Bank",
    "status": "Canceled"
  },
  {
    "tracking_id": "#20477",
    "product_img": "/assets/demo.png",
    "product_name": "Headphones",
    "customer": "Noah Kim",
    "date": "28/05/2022",
    "amount": 79.99,
    "payment_mode": "Cash on Delivery",
    "status": "Delivered"
  },
  {
    "tracking_id": "#20478",
    "product_img": "/assets/demo.png",
    "product_name": "Dress",
    "customer": "Olivia Brown",
    "date": "29/05/2022",
    "amount": 49.99,
    "payment_mode": "Transfer Bank",
    "status": "Process"
  },
  {
    "tracking_id": "#20479",
    "product_img": "/assets/demo.png",
    "product_name": "Jacket",
    "customer": "Peter Johnson",
    "date": "30/05/2022",
    "amount": 79.99,
    "payment_mode": "Cash on Delivery",
    "status": "Canceled"
  },
  {
    "tracking_id": "#20480",
    "product_img": "/assets/demo.png",
    "product_name": "Skirt",
    "customer": "Rose Davis",
    "date": "31/05/2022",
    "amount": 39.99,
    "payment_mode": "Transfer Bank",
    "status": "Delivered"
  },
  {
    "tracking_id": "#20481",
    "product_img": "/assets/demo.png",
    "product_name": "Tie",
    "customer": "Steven Miller",
    "date": "01/06/2022",
    "amount": 9.99,
    "payment_mode": "Cash on Delivery",
    "status": "Process"
  },
  {
    "tracking_id": "#20482",
    "product_img": "/assets/demo.png",
    "product_name": "Belt",
    "customer": "Taylor Clark",
    "date": "02/06/2022",
    "amount": 14.99,
    "payment_mode": "Transfer Bank",
    "status": "Canceled"
  },
  {
    "tracking_id": "#20483",
    "product_img": "/assets/demo.png",
    "product_name": "Socks",
    "customer": "Uma Rodriguez",
    "date": "03/06/2022",
    "amount": 5.99,
    "payment_mode": "Cash on Delivery",
    "status": "Delivered"
  },
  {
    "tracking_id": "#20484",
    "product_img": "/assets/demo.png",
    "product_name": "Gloves",
    "customer": "Victor Wilson",
    "date": "04/06/2022",
    "amount": 12.99,
    "payment_mode": "Transfer Bank",
    "status": "Process"
  },
  {
    "tracking_id": "#20485",
    "product_img": "/assets/demo.png",
    "product_name": "Scarf",
    "customer": "William Thompson",
    "date": "05/06/2022",
    "amount": 17.99,
    "payment_mode": "Cash on Delivery",
    "status": "Canceled"
  },
  {
    "tracking_id": "#20486",
    "product_img": "/assets/demo.png",
    "product_name": "Hat",
    "customer": "Xavier Lee",
    "date": "06/06/2022",
    "amount": 4.99,
    "payment_mode": "Transfer Bank",
    "status": "Delivered"
  },
  {
    "tracking_id": "#20487",
    "product_img": "/assets/demo.png",
    "product_name": "Shirt",
    "customer": "Yuna Garcia",
    "date": "07/06/2022",
    "amount": 19.99,
    "payment_mode": "Cash on Delivery",
    "status": "Process"
  },
  {
    "tracking_id": "#20488",
    "product_img": "/assets/demo.png",
    "product_name": "Smartwatch",
    "customer": "Zoe Kim",
    "date": "08/06/2022",
    "amount": 199.99,
    "payment_mode": "Transfer Bank",
    "status": "Canceled"
  }
]
